README.md
setup.py
Flask_Validate.egg-info/PKG-INFO
Flask_Validate.egg-info/SOURCES.txt
Flask_Validate.egg-info/dependency_links.txt
Flask_Validate.egg-info/requires.txt
Flask_Validate.egg-info/top_level.txt
flask_validate/__init__.py
flask_validate/__version__.py
flask_validate/validators.py