Metadata-Version: 1.1
Name: Flask-Validate
Version: 0.1.0
Summary: A request validator for Flask, including information in headers, query_string and request body.
Home-page: UNKNOWN
Author: zhangguangchao
Author-email: zhangguangchao@youzan.com
License: UNKNOWN
Platform: UNKNOWN
Classifier: Framework :: Flask
Classifier: Programming Language :: Python :: 2
Classifier: Programming Language :: Python :: 2.7
